exceptionalpy
