Metadata-Version: 2.1
Name: exceptionalpy
Version: 0.3
Summary: global exception handler with notification and timing features
Home-page: https://github.com/nbdy/exceptionalpy
Author: Pascal Eberlein
Author-email: pascal@eberlein.io
License: UNKNOWN
Platform: UNKNOWN
Classifier: Intended Audience :: Developers
Classifier: Topic :: Software Development :: Build Tools
Classifier: License :: OSI Approved :: MIT License
